macrometa_target_snowflake/__init__.py
macrometa_target_snowflake/db_sync.py
macrometa_target_snowflake/exceptions.py
macrometa_target_snowflake/file_format.py
macrometa_target_snowflake/flattening.py
macrometa_target_snowflake/stream_utils.py
macrometa_target_snowflake/file_formats/__init__.py
macrometa_target_snowflake/file_formats/csv.py
macrometa_target_snowflake/file_formats/parquet.py
macrometa_target_snowflake/upload_clients/__init__.py
macrometa_target_snowflake/upload_clients/base_upload_client.py
macrometa_target_snowflake/upload_clients/s3_upload_client.py
macrometa_target_snowflake/upload_clients/snowflake_upload_client.py
macrometa_target_snowflake-1.0.0.dist-info/LICENSE
macrometa_target_snowflake-1.0.0.dist-info/METADATA
macrometa_target_snowflake-1.0.0.dist-info/WHEEL
macrometa_target_snowflake-1.0.0.dist-info/entry_points.txt
macrometa_target_snowflake-1.0.0.dist-info/top_level.txt
macrometa_target_snowflake-1.0.0.dist-info/RECORD
