Metadata-Version: 2.1
Name: macrometa-target-snowflake
Version: 1.0.0
Summary: Macrometa target for loading data to Snowflake
Home-page: https://github.com/Macrometacorp/macrometa-target-snowflake
Author: Macrometa
Classifier: License :: OSI Approved :: Apache Software License
Classifier: Programming Language :: Python :: 3 :: Only
Classifier: Programming Language :: Python :: 3.7
Classifier: Programming Language :: Python :: 3.8
Classifier: Programming Language :: Python :: 3.9
Requires-Python: >=3.7
License-File: LICENSE
Requires-Dist: pipelinewise-singer-python (==1.2.0)
Requires-Dist: snowflake-connector-python[pandas] (==2.7.*)
Requires-Dist: inflection (==0.5.1)
Requires-Dist: joblib (==1.2.0)
Requires-Dist: boto3 (==1.23.10)
Requires-Dist: c8connector (>=0.0.29)
Requires-Dist: prometheus-client (==0.16.0)
Provides-Extra: test
Requires-Dist: pylint (==2.12.*) ; extra == 'test'
Requires-Dist: pytest (==7.0.1) ; extra == 'test'
Requires-Dist: pytest-cov (==4.0.0) ; extra == 'test'
Requires-Dist: python-dotenv (==0.19.*) ; extra == 'test'
